aflight/__init__.py
aflight/__main__.py
aflight/app.py
aflight/client.py
aflight/exec.py
aflight/log.py
aflight-0.2.4.dist-info/LICENSE
aflight-0.2.4.dist-info/METADATA
aflight-0.2.4.dist-info/WHEEL
aflight-0.2.4.dist-info/entry_points.txt
aflight-0.2.4.dist-info/top_level.txt
aflight-0.2.4.dist-info/RECORD
