Metadata-Version: 2.1
Name: aflight
Version: 0.2.4
Summary: Arrow Flight simple API service
Home-page: https://github.com/pkit/aflight/
Author: Constantine Peresypkin
License-File: LICENSE
Requires-Dist: pyarrow (~=11.0.0)
Requires-Dist: pandas (~=1.5.3)
Requires-Dist: setuptools (~=65.5.1)
Requires-Dist: click (~=8.1.3)
Provides-Extra: test
